<?xml version="1.0" encoding="utf-8"?>
<TextureAtlas imagePath="burito new.png">
	<!-- Created with Adobe Animate version 22.0.4.185 -->
	<!-- http://www.adobe.com/products/animate.html -->
	<SubTexture name="down0000" x="1" y="1" width="481" height="854" frameX="0" frameY="0" frameWidth="481" frameHeight="855"/>
	<SubTexture name="down0001" x="485" y="1" width="481" height="805" frameX="0" frameY="-49" frameWidth="481" frameHeight="855"/>
	<SubTexture name="down0002" x="969" y="1" width="481" height="738" frameX="0" frameY="-116" frameWidth="481" frameHeight="855"/>
	<SubTexture name="down0003" x="1453" y="1" width="481" height="641" frameX="0" frameY="-213" frameWidth="481" frameHeight="855"/>
	<SubTexture name="down0004" x="1937" y="1" width="481" height="496" frameX="0" frameY="-358" frameWidth="481" frameHeight="855"/>
	<SubTexture name="down0005" x="2421" y="1" width="481" height="400" frameX="0" frameY="-454" frameWidth="481" frameHeight="855"/>
	<SubTexture name="down0006" x="2905" y="1" width="481" height="445" frameX="0" frameY="-409" frameWidth="481" frameHeight="855"/>
	<SubTexture name="down0007" x="3389" y="1" width="481" height="476" frameX="0" frameY="-379" frameWidth="481" frameHeight="855"/>
	<SubTexture name="down0008" x="3873" y="1" width="481" height="497" frameX="0" frameY="-358" frameWidth="481" frameHeight="855"/>
	<SubTexture name="down0009" x="4357" y="1" width="481" height="512" frameX="0" frameY="-342" frameWidth="481" frameHeight="855"/>
	<SubTexture name="down0010" x="4841" y="1" width="481" height="526" frameX="0" frameY="-329" frameWidth="481" frameHeight="855"/>
	<SubTexture name="down0011" x="5325" y="1" width="481" height="536" frameX="0" frameY="-319" frameWidth="481" frameHeight="855"/>
	<SubTexture name="down0012" x="5809" y="1" width="481" height="543" frameX="0" frameY="-311" frameWidth="481" frameHeight="855"/>
	<SubTexture name="down0013" x="6293" y="1" width="481" height="550" frameX="0" frameY="-305" frameWidth="481" frameHeight="855"/>
	<SubTexture name="down0014" x="6777" y="1" width="481" height="556" frameX="0" frameY="-299" frameWidth="481" frameHeight="855"/>
	<SubTexture name="down0015" x="7261" y="1" width="481" height="559" frameX="0" frameY="-295" frameWidth="481" frameHeight="855"/>
	<SubTexture name="down0016" x="1" y="858" width="481" height="564" frameX="0" frameY="-291" frameWidth="481" frameHeight="855"/>
	<SubTexture name="down0017" x="485" y="858" width="481" height="567" frameX="0" frameY="-288" frameWidth="481" frameHeight="855"/>
	<SubTexture name="down0018" x="969" y="858" width="481" height="569" frameX="0" frameY="-286" frameWidth="481" frameHeight="855"/>
	<SubTexture name="down0019" x="1453" y="858" width="481" height="571" frameX="0" frameY="-284" frameWidth="481" frameHeight="855"/>
	<SubTexture name="down0020" x="1937" y="858" width="481" height="571" frameX="0" frameY="-283" frameWidth="481" frameHeight="855"/>
	<SubTexture name="down0021" x="2421" y="858" width="481" height="572" frameX="0" frameY="-282" frameWidth="481" frameHeight="855"/>
	<SubTexture name="down0022" x="2905" y="858" width="481" height="574" frameX="0" frameY="-281" frameWidth="481" frameHeight="855"/>
	<SubTexture name="down0023" x="3389" y="858" width="481" height="574" frameX="0" frameY="-281" frameWidth="481" frameHeight="855"/>
	<SubTexture name="idle0000" x="3873" y="858" width="481" height="280" frameX="0" frameY="-574" frameWidth="481" frameHeight="854"/>
	<SubTexture name="idle0001" x="4357" y="858" width="481" height="308" frameX="0" frameY="-546" frameWidth="481" frameHeight="854"/>
	<SubTexture name="idle0002" x="4841" y="858" width="481" height="347" frameX="0" frameY="-507" frameWidth="481" frameHeight="854"/>
	<SubTexture name="idle0003" x="5325" y="858" width="481" height="404" frameX="0" frameY="-450" frameWidth="481" frameHeight="854"/>
	<SubTexture name="idle0004" x="5809" y="858" width="481" height="488" frameX="0" frameY="-366" frameWidth="481" frameHeight="854"/>
	<SubTexture name="idle0005" x="6293" y="858" width="481" height="584" frameX="0" frameY="-270" frameWidth="481" frameHeight="854"/>
	<SubTexture name="idle0006" x="6777" y="858" width="481" height="654" frameX="0" frameY="-200" frameWidth="481" frameHeight="854"/>
	<SubTexture name="idle0007" x="7261" y="858" width="481" height="701" frameX="0" frameY="-153" frameWidth="481" frameHeight="854"/>
	<SubTexture name="idle0008" x="1" y="1562" width="481" height="734" frameX="0" frameY="-120" frameWidth="481" frameHeight="854"/>
	<SubTexture name="idle0009" x="485" y="1562" width="481" height="759" frameX="0" frameY="-95" frameWidth="481" frameHeight="854"/>
	<SubTexture name="idle0010" x="969" y="1562" width="481" height="779" frameX="0" frameY="-75" frameWidth="481" frameHeight="854"/>
	<SubTexture name="idle0011" x="1453" y="1562" width="481" height="795" frameX="0" frameY="-59" frameWidth="481" frameHeight="854"/>
	<SubTexture name="idle0012" x="1937" y="1562" width="481" height="807" frameX="0" frameY="-47" frameWidth="481" frameHeight="854"/>
	<SubTexture name="idle0013" x="2421" y="1562" width="481" height="818" frameX="0" frameY="-36" frameWidth="481" frameHeight="854"/>
	<SubTexture name="idle0014" x="2905" y="1562" width="481" height="826" frameX="0" frameY="-28" frameWidth="481" frameHeight="854"/>
	<SubTexture name="idle0015" x="3389" y="1562" width="481" height="833" frameX="0" frameY="-21" frameWidth="481" frameHeight="854"/>
	<SubTexture name="idle0016" x="3873" y="1562" width="481" height="839" frameX="0" frameY="-15" frameWidth="481" frameHeight="854"/>
	<SubTexture name="idle0017" x="4357" y="1562" width="481" height="844" frameX="0" frameY="-10" frameWidth="481" frameHeight="854"/>
	<SubTexture name="idle0018" x="4841" y="1562" width="481" height="847" frameX="0" frameY="-7" frameWidth="481" frameHeight="854"/>
	<SubTexture name="idle0019" x="5325" y="1562" width="481" height="850" frameX="0" frameY="-4" frameWidth="481" frameHeight="854"/>
	<SubTexture name="idle0020" x="5809" y="1562" width="481" height="852" frameX="0" frameY="-2" frameWidth="481" frameHeight="854"/>
	<SubTexture name="idle0021" x="6293" y="1562" width="481" height="853" frameX="0" frameY="-1" frameWidth="481" frameHeight="854"/>
	<SubTexture name="idle0022" x="6777" y="1562" width="481" height="854"/>
	<SubTexture name="idle0023" x="6777" y="1562" width="481" height="854"/>
	<SubTexture name="left0000" x="7261" y="1562" width="481" height="854"/>
	<SubTexture name="left0001" x="1" y="2419" width="454" height="854" frameX="-13" frameY="0" frameWidth="481" frameHeight="854"/>
	<SubTexture name="left0002" x="458" y="2419" width="416" height="854" frameX="-32" frameY="0" frameWidth="481" frameHeight="854"/>
	<SubTexture name="left0003" x="877" y="2419" width="363" height="854" frameX="-59" frameY="0" frameWidth="481" frameHeight="854"/>
	<SubTexture name="left0004" x="1243" y="2419" width="282" height="854" frameX="-99" frameY="0" frameWidth="481" frameHeight="854"/>
	<SubTexture name="left0005" x="1528" y="2419" width="276" height="854" frameX="-102" frameY="0" frameWidth="481" frameHeight="854"/>
	<SubTexture name="left0006" x="1807" y="2419" width="319" height="854" frameX="-81" frameY="0" frameWidth="481" frameHeight="854"/>
	<SubTexture name="left0007" x="2129" y="2419" width="347" height="854" frameX="-67" frameY="0" frameWidth="481" frameHeight="854"/>
	<SubTexture name="left0008" x="2479" y="2419" width="368" height="854" frameX="-56" frameY="0" frameWidth="481" frameHeight="854"/>
	<SubTexture name="left0009" x="2850" y="2419" width="383" height="854" frameX="-49" frameY="0" frameWidth="481" frameHeight="854"/>
	<SubTexture name="left0010" x="3236" y="2419" width="395" height="854" frameX="-43" frameY="0" frameWidth="481" frameHeight="854"/>
	<SubTexture name="left0011" x="3634" y="2419" width="404" height="854" frameX="-38" frameY="0" frameWidth="481" frameHeight="854"/>
	<SubTexture name="left0012" x="4041" y="2419" width="412" height="854" frameX="-34" frameY="0" frameWidth="481" frameHeight="854"/>
	<SubTexture name="left0013" x="4456" y="2419" width="419" height="854" frameX="-31" frameY="0" frameWidth="481" frameHeight="854"/>
	<SubTexture name="left0014" x="4878" y="2419" width="424" height="854" frameX="-28" frameY="0" frameWidth="481" frameHeight="854"/>
	<SubTexture name="left0015" x="5305" y="2419" width="428" height="854" frameX="-26" frameY="0" frameWidth="481" frameHeight="854"/>
	<SubTexture name="left0016" x="5736" y="2419" width="432" height="854" frameX="-24" frameY="0" frameWidth="481" frameHeight="854"/>
	<SubTexture name="left0017" x="6171" y="2419" width="434" height="854" frameX="-23" frameY="0" frameWidth="481" frameHeight="854"/>
	<SubTexture name="left0018" x="6608" y="2419" width="436" height="854" frameX="-22" frameY="0" frameWidth="481" frameHeight="854"/>
	<SubTexture name="left0019" x="7047" y="2419" width="438" height="854" frameX="-21" frameY="0" frameWidth="481" frameHeight="854"/>
	<SubTexture name="left0020" x="7488" y="2419" width="440" height="854" frameX="-20" frameY="0" frameWidth="481" frameHeight="854"/>
	<SubTexture name="left0021" x="1" y="3276" width="440" height="854" frameX="-20" frameY="0" frameWidth="481" frameHeight="854"/>
	<SubTexture name="left0022" x="444" y="3276" width="441" height="854" frameX="-20" frameY="0" frameWidth="481" frameHeight="854"/>
	<SubTexture name="left0023" x="888" y="3276" width="441" height="854" frameX="-20" frameY="0" frameWidth="481" frameHeight="854"/>
	<SubTexture name="right0000" x="1332" y="3276" width="481" height="854"/>
	<SubTexture name="right0001" x="1816" y="3276" width="458" height="854" frameX="-12" frameY="0" frameWidth="481" frameHeight="854"/>
	<SubTexture name="right0002" x="2277" y="3276" width="426" height="854" frameX="-28" frameY="0" frameWidth="481" frameHeight="854"/>
	<SubTexture name="right0003" x="2706" y="3276" width="379" height="854" frameX="-51" frameY="0" frameWidth="481" frameHeight="854"/>
	<SubTexture name="right0004" x="3088" y="3276" width="310" height="854" frameX="-86" frameY="0" frameWidth="481" frameHeight="854"/>
	<SubTexture name="right0005" x="3401" y="3276" width="304" height="854" frameX="-89" frameY="0" frameWidth="481" frameHeight="854"/>
	<SubTexture name="right0006" x="3708" y="3276" width="339" height="854" frameX="-71" frameY="0" frameWidth="481" frameHeight="854"/>
	<SubTexture name="right0007" x="4050" y="3276" width="363" height="854" frameX="-59" frameY="0" frameWidth="481" frameHeight="854"/>
	<SubTexture name="right0008" x="4416" y="3276" width="380" height="854" frameX="-51" frameY="0" frameWidth="481" frameHeight="854"/>
	<SubTexture name="right0009" x="4799" y="3276" width="392" height="854" frameX="-45" frameY="0" frameWidth="481" frameHeight="854"/>
	<SubTexture name="right0010" x="5194" y="3276" width="402" height="854" frameX="-40" frameY="0" frameWidth="481" frameHeight="854"/>
	<SubTexture name="right0011" x="5599" y="3276" width="410" height="854" frameX="-36" frameY="0" frameWidth="481" frameHeight="854"/>
	<SubTexture name="right0012" x="6012" y="3276" width="417" height="854" frameX="-32" frameY="0" frameWidth="481" frameHeight="854"/>
	<SubTexture name="right0013" x="6432" y="3276" width="422" height="854" frameX="-30" frameY="0" frameWidth="481" frameHeight="854"/>
	<SubTexture name="right0014" x="6857" y="3276" width="426" height="854" frameX="-28" frameY="0" frameWidth="481" frameHeight="854"/>
	<SubTexture name="right0015" x="7286" y="3276" width="430" height="854" frameX="-26" frameY="0" frameWidth="481" frameHeight="854"/>
	<SubTexture name="right0016" x="7719" y="3276" width="434" height="854" frameX="-24" frameY="0" frameWidth="481" frameHeight="854"/>
	<SubTexture name="right0017" x="1" y="4133" width="436" height="854" frameX="-23" frameY="0" frameWidth="481" frameHeight="854"/>
	<SubTexture name="right0018" x="440" y="4133" width="438" height="854" frameX="-22" frameY="0" frameWidth="481" frameHeight="854"/>
	<SubTexture name="right0019" x="881" y="4133" width="438" height="854" frameX="-22" frameY="0" frameWidth="481" frameHeight="854"/>
	<SubTexture name="right0020" x="1322" y="4133" width="440" height="854" frameX="-21" frameY="0" frameWidth="481" frameHeight="854"/>
	<SubTexture name="right0021" x="1765" y="4133" width="440" height="854" frameX="-21" frameY="0" frameWidth="481" frameHeight="854"/>
	<SubTexture name="right0022" x="2208" y="4133" width="440" height="854" frameX="-21" frameY="0" frameWidth="481" frameHeight="854"/>
	<SubTexture name="right0023" x="2651" y="4133" width="441" height="854" frameX="-20" frameY="0" frameWidth="481" frameHeight="854"/>
	<SubTexture name="up0000" x="3095" y="4133" width="480" height="854" frameX="0" frameY="-595" frameWidth="480" frameHeight="1450"/>
	<SubTexture name="up0001" x="3578" y="4133" width="480" height="901" frameX="0" frameY="-549" frameWidth="480" frameHeight="1450"/>
	<SubTexture name="up0002" x="4061" y="4133" width="480" height="962" frameX="0" frameY="-487" frameWidth="480" frameHeight="1450"/>
	<SubTexture name="up0003" x="4544" y="4133" width="480" height="1053" frameX="0" frameY="-397" frameWidth="480" frameHeight="1450"/>
	<SubTexture name="up0004" x="5027" y="4133" width="480" height="1186" frameX="0" frameY="-263" frameWidth="480" frameHeight="1450"/>
	<SubTexture name="up0005" x="5510" y="4133" width="480" height="1339" frameX="0" frameY="-111" frameWidth="480" frameHeight="1450"/>
	<SubTexture name="up0006" x="5993" y="4133" width="480" height="1450"/>
	<SubTexture name="up0007" x="6476" y="4133" width="480" height="1415" frameX="0" frameY="-34" frameWidth="480" frameHeight="1450"/>
	<SubTexture name="up0008" x="6959" y="4133" width="480" height="1391" frameX="0" frameY="-59" frameWidth="480" frameHeight="1450"/>
	<SubTexture name="up0009" x="7442" y="4133" width="480" height="1371" frameX="0" frameY="-79" frameWidth="480" frameHeight="1450"/>
	<SubTexture name="up0010" x="1" y="5586" width="480" height="1355" frameX="0" frameY="-94" frameWidth="480" frameHeight="1450"/>
	<SubTexture name="up0011" x="484" y="5586" width="480" height="1344" frameX="0" frameY="-106" frameWidth="480" frameHeight="1450"/>
	<SubTexture name="up0012" x="967" y="5586" width="480" height="1334" frameX="0" frameY="-116" frameWidth="480" frameHeight="1450"/>
	<SubTexture name="up0013" x="1450" y="5586" width="480" height="1326" frameX="0" frameY="-124" frameWidth="480" frameHeight="1450"/>
	<SubTexture name="up0014" x="1933" y="5586" width="480" height="1320" frameX="0" frameY="-130" frameWidth="480" frameHeight="1450"/>
	<SubTexture name="up0015" x="2416" y="5586" width="480" height="1315" frameX="0" frameY="-135" frameWidth="480" frameHeight="1450"/>
	<SubTexture name="up0016" x="2899" y="5586" width="480" height="1310" frameX="0" frameY="-140" frameWidth="480" frameHeight="1450"/>
	<SubTexture name="up0017" x="3382" y="5586" width="480" height="1307" frameX="0" frameY="-143" frameWidth="480" frameHeight="1450"/>
	<SubTexture name="up0018" x="3865" y="5586" width="480" height="1304" frameX="0" frameY="-146" frameWidth="480" frameHeight="1450"/>
	<SubTexture name="up0019" x="4348" y="5586" width="480" height="1302" frameX="0" frameY="-148" frameWidth="480" frameHeight="1450"/>
	<SubTexture name="up0020" x="4831" y="5586" width="480" height="1300" frameX="0" frameY="-150" frameWidth="480" frameHeight="1450"/>
	<SubTexture name="up0021" x="5314" y="5586" width="480" height="1299" frameX="0" frameY="-151" frameWidth="480" frameHeight="1450"/>
	<SubTexture name="up0022" x="5797" y="5586" width="480" height="1299" frameX="0" frameY="-151" frameWidth="480" frameHeight="1450"/>
	<SubTexture name="up0023" x="5797" y="5586" width="480" height="1299" frameX="0" frameY="-152" frameWidth="480" frameHeight="1450"/>
</TextureAtlas>
